{
	"file_path": "",
	"grader_id": "",
	"annotations": [
		{
			"type": "drawing",
			"lines": [["519.40","18.60"],["521.00","21.00"],["523.40","24.20"],["529.00","29.80"],["533.00","34.60"],["537.80","41.00"],["541.00","45.00"],["544.20","49.00"],["546.60","52.20"],["549.00","55.40"],["549.00","57.00"],["550.60","58.60"],["551.40","59.40"],["551.40","60.20"],["551.40","61.00"],["552.20","61.80"]],
			"class": "Annotation",
			"uuid": "f0859f3e-5528-4417-8d4a-17f635f4cbb8",
			"page": 1,
			"userId": ""
		},

		{
			"type": "drawing",
			"lines": [["541.00","23.40"],["536.20","28.20"],["532.20","33.80"],["531.40","35.40"],["530.60","36.20"],["529.80","37.80"],["529.00","38.60"],["529.00","39.40"],["528.20","41.00"],["527.40","41.80"],["526.60","42.60"],["525.80","42.60"],["525.80","43.40"],["525.00","44.20"],["523.40","46.60"],["521.00","49.80"],["519.40","51.40"],["518.60","53.00"],["517.80","53.00"],["517.00","54.60"],["516.20","54.60"],["516.20","55.40"],["515.40","56.20"],["514.60","56.20"],["513.80","56.20"],["513.00","56.20"],["513.00","55.40"]],
			"class": "Annotation",
			"uuid": "68cfad74-7c6a-42c8-8a77-e94af00408e8",
			"page": 1,
			"userId": ""
		},
		
		{
			"type": "textbox",
			"size": 12,
			"color": "#000000",
			"content": "ANNOTATION\n",
			"x": 514.3999633789062,
			"y": 76.80000305175781,
			"rotation": 0,
			"class": "Annotation",
			"uuid": "9c407e20-472f-4c62-98d6-6a74c1b1f052",
			"page": 1,
			"userId": ""
		}
	]
}